vernamcipher/__init__.py
vernamcipher/cryptographic.py
vernamcipher-1.1.5.dist-info/LICENSE
vernamcipher-1.1.5.dist-info/METADATA
vernamcipher-1.1.5.dist-info/WHEEL
vernamcipher-1.1.5.dist-info/top_level.txt
vernamcipher-1.1.5.dist-info/RECORD
