Metadata-Version: 2.1
Name: vernamcipher
Version: 1.1.5
Summary: A Python implementation of truly-random Vernam Cipher encryption.
Home-page: https://github.com/mo-awais/vernamcipher
Author: Mohammed Awais
Author-email: awais@mohammedawais.me
License: UNKNOWN
Platform: UNKNOWN
Classifier: Programming Language :: Python :: 3.8
Classifier: Programming Language :: Python :: 3.10
Classifier: License :: OSI Approved :: GNU Affero General Public License v3
Requires-Dist: requests (>=2.27.1)
